setup.cfg
setup.py
asterisk_dialplan/__init__.py
asterisk_dialplan/dialplan.py
asterisk_dialplan/dialplan_exceptions.py
asterisk_dialplan/patterns.py
asterisk_dialplan/ranges.py
asterisk_dialplan/tests.py
asterisk_dialplan/util.py
asterisk_dialplan.egg-info/PKG-INFO
asterisk_dialplan.egg-info/SOURCES.txt
asterisk_dialplan.egg-info/dependency_links.txt
asterisk_dialplan.egg-info/top_level.txt