Metadata-Version: 1.1
Name: asterisk_dialplan
Version: 0.1.3
Summary: Helpers to convert numbers to dialplan strings for use in Asterisk
Home-page: UNKNOWN
Author: Andrew Yager
Author-email: andrew@rwts.com.au
License: BSD
Platform: UNKNOWN
Classifier: Development Status :: 4 - Beta
Classifier: Topic :: Communications :: Telephony
Classifier: Topic :: Software Development :: Libraries
Classifier: License :: OSI Approved :: BSD License
